nrdtech_aws_utils/__init__.py
nrdtech_aws_utils/dynamodb_table.py
nrdtech_aws_utils/firehose_helper.py
nrdtech_aws_utils/s3_helper.py
nrdtech_aws_utils/secrets_helper.py
nrdtech_aws_utils/sqs_helper.py
nrdtech_aws_utils-0.0.5.dist-info/licenses/LICENSE
nrdtech_aws_utils-0.0.5.dist-info/WHEEL
nrdtech_aws_utils-0.0.5.dist-info/METADATA
nrdtech_aws_utils-0.0.5.dist-info/RECORD
