Metadata-Version: 2.4
Name: nrdtech_aws_utils
Version: 0.0.5
Summary: A library of helpful wrappers around boto3 aws functions
Author-email: Nic Delorme <nic.delorme@nrdtech.io>
Requires-Python: >=3.10
Classifier: Development Status :: 3 - Alpha
Classifier: Intended Audience :: Developers
Classifier: License :: OSI Approved :: MIT License
Classifier: Programming Language :: Python :: 3
Classifier: Programming Language :: Python :: 3.10
Classifier: Operating System :: OS Independent
License-File: LICENSE
Requires-Dist: nrdtech-utils~=0.0.3
Requires-Dist: boto3~=1.34.67
Requires-Dist: pandas~=2.2.0
Requires-Dist: pyarrow>=17.0.0
Project-URL: Repository, https://github.com/NRD-Tech/nrdtech-aws-utils
